ddeutil/df/__about__.py
ddeutil/df/__init__.py
ddeutil/df/pandas/__init__.py
ddeutil/df/polars/__init__.py
ddeutil/df/polars/database.py
ddeutil/df/polars/deltalake.py
ddeutil/df/pyspark/__init__.py
ddeutil/df/pyspark/client.py
ddeutil_df-0.0.1.dist-info/LICENSE
ddeutil_df-0.0.1.dist-info/METADATA
ddeutil_df-0.0.1.dist-info/WHEEL
ddeutil_df-0.0.1.dist-info/top_level.txt
ddeutil_df-0.0.1.dist-info/RECORD
